yahoo_quote_download/__init__.py
yahoo_quote_download/downloader.py
yahoo_quote_download/validater.py
yahoo_quote_download/yqd.py
yahoo_quote_download-0.3.2.dist-info/METADATA
yahoo_quote_download-0.3.2.dist-info/WHEEL
yahoo_quote_download-0.3.2.dist-info/entry_points.txt
yahoo_quote_download-0.3.2.dist-info/top_level.txt
yahoo_quote_download-0.3.2.dist-info/RECORD
