Metadata-Version: 2.1
Name: yahoo-quote-download
Version: 0.3.2
Summary: Yahoo Quote Downloader
Home-page: https://github.com/c0redumb/yahoo_quote_download
Author: c0redumb
License: BSD 2-Clause License
Platform: UNKNOWN
Classifier: Programming Language :: Python :: 2
Classifier: Programming Language :: Python :: 3
Classifier: License :: OSI Approved :: BSD License
Classifier: Operating System :: OS Independent
Requires-Dist: six
